Changelog
MANIFEST.in
README
setup.py
bin/boty
bin/boty-xmpp
boty/__init__.py
boty/imports.py
boty/version.py
boty.egg-info/PKG-INFO
boty.egg-info/SOURCES.txt
boty.egg-info/dependency_links.txt
boty.egg-info/not-zip-safe
boty.egg-info/top_level.txt
boty/contrib/__init__.py
boty/contrib/sleekxmpp/__init__.py
boty/contrib/sleekxmpp/basexmpp.py
boty/contrib/sleekxmpp/clientxmpp.py
boty/contrib/sleekxmpp/componentxmpp.py
boty/contrib/sleekxmpp/exceptions.py
boty/contrib/sleekxmpp/version.py
boty/contrib/sleekxmpp/features/__init__.py
boty/contrib/sleekxmpp/features/feature_bind/__init__.py
boty/contrib/sleekxmpp/features/feature_bind/bind.py
boty/contrib/sleekxmpp/features/feature_bind/stanza.py
boty/contrib/sleekxmpp/features/feature_mechanisms/__init__.py
boty/contrib/sleekxmpp/features/feature_mechanisms/mechanisms.py
boty/contrib/sleekxmpp/features/feature_mechanisms/stanza/__init__.py
boty/contrib/sleekxmpp/features/feature_mechanisms/stanza/auth.py
boty/contrib/sleekxmpp/features/feature_mechanisms/stanza/challenge.py
boty/contrib/sleekxmpp/features/feature_mechanisms/stanza/failure.py
boty/contrib/sleekxmpp/features/feature_mechanisms/stanza/mechanisms.py
boty/contrib/sleekxmpp/features/feature_mechanisms/stanza/response.py
boty/contrib/sleekxmpp/features/feature_mechanisms/stanza/success.py
boty/contrib/sleekxmpp/features/feature_session/__init__.py
boty/contrib/sleekxmpp/features/feature_session/session.py
boty/contrib/sleekxmpp/features/feature_session/stanza.py
boty/contrib/sleekxmpp/features/feature_starttls/__init__.py
boty/contrib/sleekxmpp/features/feature_starttls/stanza.py
boty/contrib/sleekxmpp/features/feature_starttls/starttls.py
boty/contrib/sleekxmpp/plugins/__init__.py
boty/contrib/sleekxmpp/plugins/base.py
boty/contrib/sleekxmpp/plugins/gmail_notify.py
boty/contrib/sleekxmpp/plugins/jobs.py
boty/contrib/sleekxmpp/plugins/old_0004.py
boty/contrib/sleekxmpp/plugins/old_0009.py
boty/contrib/sleekxmpp/plugins/old_0050.py
boty/contrib/sleekxmpp/plugins/old_0060.py
boty/contrib/sleekxmpp/plugins/xep_0012.py
boty/contrib/sleekxmpp/plugins/xep_0033.py
