Metadata-Version: 1.1
Name: boty
Version: 0.1.1
Summary: Time Flies
Home-page: http://boty.googlecode.com/
Author: Bart Thate
Author-email: bthate@gmail.com
License: MIT
Download-URL: http://code.google.com/p/boty/downloads
Platform: UNKNOWN
Classifier: Development Status :: 3 - Alpha
Classifier: Environment :: Console
Classifier: Environment :: Other Environment
Classifier: Intended Audience :: Developers
Classifier: License :: OSI Approved :: MIT License
Classifier: Operating System :: Unix
Classifier: Programming Language :: Python
Classifier: Topic :: Communications :: Chat
Classifier: Topic :: Software Development :: Libraries :: Python Modules
Requires: jsb
Requires: dnspython
